AUTHORS
CHANGELOG.txt
DESCRIPTION
LICENSE
MANIFEST.in
README.rst
setup.py
django_paypal_express_checkout.egg-info/PKG-INFO
django_paypal_express_checkout.egg-info/SOURCES.txt
django_paypal_express_checkout.egg-info/dependency_links.txt
django_paypal_express_checkout.egg-info/requires.txt
django_paypal_express_checkout.egg-info/top_level.txt
paypal_express_checkout/__init__.py
paypal_express_checkout/admin.py
paypal_express_checkout/constants.py
paypal_express_checkout/forms.py
paypal_express_checkout/models.py
paypal_express_checkout/settings.py
paypal_express_checkout/signals.py
paypal_express_checkout/urls.py
paypal_express_checkout/utils.py
paypal_express_checkout/views.py
paypal_express_checkout/migrations/0001_initial.py
paypal_express_checkout/migrations/__init__.py
paypal_express_checkout/south_migrations/0001_initial.py
paypal_express_checkout/south_migrations/0002_auto__add_field_paymenttransaction_content_type__add_field_paymenttran.py
paypal_express_checkout/south_migrations/0003_auto__add_purchaseditem.py
paypal_express_checkout/south_migrations/0004_auto__chg_field_purchaseditem_item.py
paypal_express_checkout/south_migrations/0005_auto__add_field_item_identifier.py
paypal_express_checkout/south_migrations/0006_auto__add_field_paymenttransactionerror_paypal_api_url__add_field_paym.py
paypal_express_checkout/south_migrations/0007_auto__add_field_item_currency.py
paypal_express_checkout/south_migrations/0008_auto__add_field_purchaseditem_content_type__add_field_purchaseditem_ob.py
paypal_express_checkout/south_migrations/0009_auto__add_field_purchaseditem_price.py
paypal_express_checkout/south_migrations/0010_auto__add_field_purchaseditem_identifier.py
paypal_express_checkout/south_migrations/0011_auto__add_field_paymenttransaction_creation_date.py
paypal_express_checkout/south_migrations/0012_init_creation_date.py
paypal_express_checkout/south_migrations/__init__.py
paypal_express_checkout/templates/404.html
paypal_express_checkout/templates/base.html
paypal_express_checkout/templates/paypal_express_checkout/confirm_checkout.html
paypal_express_checkout/templates/paypal_express_checkout/error.html
paypal_express_checkout/templates/paypal_express_checkout/payment_canceled.html
