Metadata-Version: 1.0
Name: django-paypal-express-checkout
Version: 1.9
Summary: A reusable Django app to include a PayPal payment flow to your site.
